popunimation.py
popunimation-0.0.2.dist-info/METADATA
popunimation-0.0.2.dist-info/WHEEL
popunimation-0.0.2.dist-info/entry_points.txt
popunimation-0.0.2.dist-info/top_level.txt
popunimation-0.0.2.dist-info/RECORD
