Metadata-Version: 2.1
Name: popunimation
Version: 0.0.2
Summary: A package for visualizing population of countries
Home-page: https://github.com/myamamoto325/population
Author: masaki yamamoto
Author-email: yamamoto.ma25@gmail.com
License: UNKNOWN
Project-URL: Bug Tracker, https://github.com/myamamoto325/population
Platform: UNKNOWN
Classifier: Programming Language :: Python :: 3
Classifier: License :: OSI Approved :: MIT License
Classifier: Operating System :: OS Independent
Requires-Python: >=3.7
